faststrap/__init__.py
faststrap/py.typed
faststrap/components/__init__.py
faststrap/components/patterns.py
faststrap/components/advance/README.md
faststrap/components/display/__init__.py
faststrap/components/display/badge.py
faststrap/components/display/card.py
faststrap/components/display/carousel.py
faststrap/components/display/empty_state.py
faststrap/components/display/figure.py
faststrap/components/display/image.py
faststrap/components/display/sheet.py
faststrap/components/display/stat_card.py
faststrap/components/display/table.py
faststrap/components/feedback/__init__.py
faststrap/components/feedback/alert.py
faststrap/components/feedback/confirm.py
faststrap/components/feedback/install_prompt.py
faststrap/components/feedback/modal.py
faststrap/components/feedback/overlays.py
faststrap/components/feedback/placeholder.py
faststrap/components/feedback/progress.py
faststrap/components/feedback/spinner.py
faststrap/components/feedback/toast.py
faststrap/components/forms/__init__.py
faststrap/components/forms/button.py
faststrap/components/forms/buttongroup.py
faststrap/components/forms/checks.py
faststrap/components/forms/file.py
faststrap/components/forms/input.py
faststrap/components/forms/inputgroup.py
faststrap/components/forms/select.py
faststrap/components/layout/__init__.py
faststrap/components/layout/grid.py
faststrap/components/layout/hero.py
faststrap/components/navigation/__init__.py
faststrap/components/navigation/accordion.py
faststrap/components/navigation/bottom_nav.py
faststrap/components/navigation/breadcrumb.py
faststrap/components/navigation/drawer.py
faststrap/components/navigation/dropdown.py
faststrap/components/navigation/glass_navbar.py
faststrap/components/navigation/listgroup.py
faststrap/components/navigation/navbar.py
faststrap/components/navigation/pagination.py
faststrap/components/navigation/scrollspy.py
faststrap/components/navigation/sidebar_navbar.py
faststrap/components/navigation/tabs.py
faststrap/core/__init__.py
faststrap-0.5.3.dist-info/METADATA
faststrap-0.5.3.dist-info/WHEEL
faststrap-0.5.3.dist-info/licenses/LICENSE
faststrap-0.5.3.dist-info/RECORD
