Metadata-Version: 2.4
Name: faststrap
Version: 0.5.3
Summary: Modern Bootstrap 5 components for FastHTML - Build beautiful UIs in pure Python
Project-URL: Homepage, https://github.com/Faststrap-org/Faststrap
Project-URL: Repository, https://github.com/Faststrap-org/Faststrap
Project-URL: Issues, https://github.com/Faststrap-org/Faststrap/issues
Project-URL: Documentation, https://github.com/Faststrap-org/Faststrap#readme
Project-URL: Changelog, https://github.com/Faststrap-org/Faststrap/blob/main/CHANGELOG.md
Author-email: Olorundare Micheal <meshelleva@gmail.com>
License: MIT
License-File: LICENSE
Keywords: bootstrap,bootstrap5,fasthtml,htmx,no-javascript,python-web,ui-components,web-framework
Classifier: Development Status :: 3 - Alpha
Classifier: Framework :: FastAPI
Classifier: Intended Audience :: Developers
Classifier: License :: OSI Approved :: MIT License
Classifier: Programming Language :: Python :: 3
Classifier: Programming Language :: Python :: 3.10
Classifier: Programming Language :: Python :: 3.11
Classifier: Programming Language :: Python :: 3.12
Classifier: Topic :: Internet :: WWW/HTTP :: Dynamic Content
Classifier: Topic :: Software Development :: Libraries :: Python Modules
Classifier: Topic :: Software Development :: User Interfaces
Classifier: Typing :: Typed
Requires-Python: >=3.10
Requires-Dist: python-fasthtml>=0.6.0
Provides-Extra: dev
Requires-Dist: black>=24.0; extra == 'dev'
Requires-Dist: mypy>=1.5; extra == 'dev'
Requires-Dist: pytest-cov>=4.0; extra == 'dev'
Requires-Dist: pytest>=7.4; extra == 'dev'
Requires-Dist: ruff>=0.5.0; extra == 'dev'
